usama/__init__.py
usama/core.py
usama-5.1.1.dist-info/METADATA
usama-5.1.1.dist-info/WHEEL
usama-5.1.1.dist-info/top_level.txt
usama-5.1.1.dist-info/RECORD
