Metadata-Version: 2.4
Name: usama
Version: 5.1.1
Summary: Thanks Sir
Author: Saif
Author-email: saifullahanwar.numl@gmail.com
Classifier: Programming Language :: Python :: 3
Classifier: License :: OSI Approved :: MIT License
Requires-Python: >=3.6
Dynamic: author
Dynamic: author-email
Dynamic: classifier
Dynamic: requires-python
Dynamic: summary
